LICENSE
MANIFEST.in
README.md
setup.py
FacebookSearch/FacebookSearch.py
FacebookSearch/FacebookSearchException.py
FacebookSearch/FacebookSearchOrder.py
FacebookSearch/__init__.py
FacebookSearch/utils.py
FacebookSearch.egg-info/PKG-INFO
FacebookSearch.egg-info/SOURCES.txt
FacebookSearch.egg-info/dependency_links.txt
FacebookSearch.egg-info/not-zip-safe
FacebookSearch.egg-info/requires.txt
FacebookSearch.egg-info/top_level.txt